minuto/check_oncall_rules.py
minuto/main.py
minuto-0.0.0.dist-info/METADATA
minuto-0.0.0.dist-info/WHEEL
minuto-0.0.0.dist-info/top_level.txt
minuto-0.0.0.dist-info/RECORD
