Metadata-Version: 2.4
Name: minuto
Version: 0.0.0
Summary: Calculate on-call compensation based on OpsGenie API data
Requires-Python: >=3.10
Requires-Dist: pandas
Requires-Dist: pytz
Requires-Dist: python-dateutil
Requires-Dist: holidays
Requires-Dist: matplotlib
Requires-Dist: pydantic
Requires-Dist: requests
Requires-Dist: click
Requires-Dist: python-dotenv
Requires-Dist: email-validator
Requires-Dist: icalendar
Requires-Dist: xlsxwriter
